spectre_ai/__init__.py
spectre_ai-0.0.2.dist-info/LICENSE
spectre_ai-0.0.2.dist-info/METADATA
spectre_ai-0.0.2.dist-info/WHEEL
spectre_ai-0.0.2.dist-info/top_level.txt
spectre_ai-0.0.2.dist-info/RECORD
