Metadata-Version: 2.1
Name: spectre-ai
Version: 0.0.2
Summary: Modules for Spectre AI Assistant
Home-page: https://github.com/Bazindigo
Author: Sebastian Willowhawk
Author-email: bazindigo@gmail.com
License: UNKNOWN
Platform: UNKNOWN
Classifier: Programming Language :: Python :: 3
Classifier: License :: Free To Use But Restricted
Classifier: Operating System :: OS Independent
Classifier: Natural Language :: English
Classifier: Development Status :: 1 - Planning
Requires-Python: >=3.8
